{"ongoing_trials": {"tuner0": "0002"}, "hyperparameters": {"space": [{"class_name": "Int", "config": {"name": "cnn_layers", "default": 5, "conditions": [], "min_value": 0, "max_value": 5, "step": 1, "sampling": "linear"}}, {"class_name": "Int", "config": {"name": "lstm_layers", "default": 4, "conditions": [], "min_value": 0, "max_value": 5, "step": 1, "sampling": "linear"}}, {"class_name": "Int", "config": {"name": "dense_layers", "default": 0, "conditions": [], "min_value": 0, "max_value": 5, "step": 1, "sampling": "linear"}}, {"class_name": "Int", "config": {"name": "epochs", "default": 850, "conditions": [], "min_value": 50, "max_value": 900, "step": 1, "sampling": "linear"}}, {"class_name": "Int", "config": {"name": "max_pooling", "default": 1, "conditions": [], "min_value": 0, "max_value": 1, "step": 1, "sampling": "linear"}}, {"class_name": "Int", "config": {"name": "dropout", "default": 0, "conditions": [], "min_value": 0, "max_value": 2, "step": 1, "sampling": "linear"}}, {"class_name": "Int", "config": {"name": "batch_norm", "default": 2, "conditions": [], "min_value": 0, "max_value": 2, "step": 1, "sampling": "linear"}}, {"class_name": "Int", "config": {"name": "batch_size", "default": 64, "conditions": [], "min_value": 64, "max_value": 150, "step": 1, "sampling": "linear"}}, {"class_name": "Float", "config": {"name": "learning_rate", "default": 0.0005, "conditions": [], "min_value": 0.0001, "max_value": 0.001, "step": null, "sampling": "linear"}}], "values": {"cnn_layers": 5, "lstm_layers": 4, "dense_layers": 0, "epochs": 850, "max_pooling": 1, "dropout": 0, "batch_norm": 2, "batch_size": 64, "learning_rate": 0.0005}}, "start_order": ["0000", "0001", "0002"], "end_order": ["0000", "0001"], "run_times": {"0000": 1, "0001": 1}, "retry_queue": [], "seed": 4618, "seed_state": 4645, "tried_so_far": ["48dfaf3bc040896935e616dcebc4c17f", "ad8e564eaa3ffe73159b612df3e175b8", "fcbe397c15aa8f4a8f661dd6bb16f462"], "id_to_hash": {"0000": "48dfaf3bc040896935e616dcebc4c17f", "0001": "fcbe397c15aa8f4a8f661dd6bb16f462", "0002": "ad8e564eaa3ffe73159b612df3e175b8"}, "display": {"search_start": "2024-02-15T19:30:27.125425", "trial_start": {"0000": "2024-02-15T19:30:27.125425", "0001": "2024-02-15T19:34:37.884855"}, "trial_number": {"0000": 1, "0001": 2}}, "hyperband_iterations": 1, "max_epochs": 50, "min_epochs": 1, "factor": 3, "brackets": [{"bracket_num": 3, "rounds": [[{"past_id": null, "id": "0000"}, {"past_id": null, "id": "0001"}, {"past_id": null, "id": "0002"}], [], [], []]}], "current_bracket": 3, "current_iteration": 0}